[
    {
        "receiver": "vg",
        "id": "25000003",
        "nom_complet": "vg",
        "type_de_message": "bienvenu",
        "date": "20/12/2025 19:37",
        "message": "bienvenu a Archemede school"
    },
    {
        "receiver": "vg",
        "id": 25000003,
        "nom_complet": "h,nj vg",
        "type_de_message": "observation",
        "date": "20/12/2025 21:03",
        "message": "ghgh"
    },
    {
        "receiver": "xvc",
        "id": 25000002,
        "nom_complet": "cwx xvc",
        "type_de_message": "observation",
        "date": "20/12/2025 21:03",
        "message": "gh"
    },
    {
        "receiver": "xvc",
        "id": 25000002,
        "nom_complet": "xvc",
        "type_de_message": "observation",
        "date": "2025-12-20 21:03:36",
        "message": "vous ave marke absent on 2025-12-20 pour le crenau d'jourdui."
    },
    {
        "receiver": "jix",
        "id": 25000001,
        "nom_complet": "leith jix",
        "type_de_message": "observation",
        "date": "20/12/2025 21:06",
        "message": "gg"
    },
    {
        "receiver": "jix",
        "id": 25000001,
        "nom_complet": "jix",
        "type_de_message": "observation",
        "date": "2025-12-20 21:07:54",
        "message": "vous ave marke present on 2025-12-20 pour le crenau d'jourdui."
    },
    {
        "receiver": "aissaoui",
        "id": 25090001,
        "nom_complet": "False",
        "type_de_message": "observation",
        "date": "21/12/2025 13:32",
        "message": "iyot"
    },
    {
        "receiver": "jix",
        "id": 25000001,
        "nom_complet": "False",
        "type_de_message": "observation",
        "date": "21/12/2025 13:39",
        "message": "cour anuller"
    },
    {
        "receiver": "xvc",
        "id": 25000002,
        "nom_complet": "False",
        "type_de_message": "observation",
        "date": "21/12/2025 13:39",
        "message": "cour anuller"
    },
    {
        "receiver": "all",
        "id": "all",
        "nom_complet": "all",
        "type_de_message": "observation",
        "date": "21/12/2025 13:50",
        "message": "ddd"
    },
    {
        "receiver": "jix",
        "id": 25000001,
        "nom_complet": "leith jix",
        "type_de_message": "observation",
        "date": "21/12/2025 14:18",
        "message": "dg"
    },
    {
        "receiver": "jix",
        "id": 25000001,
        "nom_complet": "False",
        "type_de_message": "observation",
        "date": "21/12/2025 14:36",
        "message": "tyrd"
    },
    {
        "receiver": "xvc",
        "id": 25000002,
        "nom_complet": "False",
        "type_de_message": "observation",
        "date": "21/12/2025 14:37",
        "message": "tyrd"
    },
    {
        "receiver": "all",
        "id": "all",
        "nom_complet": "all",
        "type_de_message": "observation",
        "date": "21/12/2025 14:37",
        "message": "yg"
    },
    {
        "receiver": "all",
        "id": "all",
        "nom_complet": "all",
        "type_de_message": "observation",
        "date": "21/12/2025 14:38",
        "message": "ff"
    },
    {
        "receiver": "all",
        "id": "all",
        "nom_complet": "all",
        "type_de_message": "observation",
        "date": "21/12/2025 14:42",
        "message": "hj"
    },
    {
        "receiver": "aissaoui",
        "id": 25090001,
        "nom_complet": "aissaoui",
        "type_de_message": "observation",
        "date": "2025-12-21 14:51:47",
        "message": "vous ave marke absent on 2025-12-21 pour le crenau d'jourdui."
    },
    {
        "receiver": "aissaoui",
        "id": 25090001,
        "nom_complet": "aissaoui",
        "type_de_message": "observation",
        "date": "2025-12-21 14:53:43",
        "message": "vous ave marke absent on 2025-12-21 pour le crenau d'jourdui."
    }
]